{
    "applicant": {
        "address": {
            "streetAddress": "525 EAST 68TH STREET",
            "zipCode": "10065",
            "city": "NEW YORK",
            "state": "NY",
            "county": "NEW YORK"
        },
        "veteranStatus": false,
        "dateOfBirth": "2002-09-30T18:30:00.000Z",
        "firstName": "ANJANA",
        "lastName": "AC",
        "primaryPhone": "(555) 555-5555",
        "email": "ANJANA@GMAIL.COM",
        "gender": "F",
        "dob": "10/01/2002"
    },
    "businessData": {
        "address": {
            "streetAddress": "525 EAST 68TH STREET",
            "zipCode": "10065",
            "city": "NEW YORK",
            "state": "NY",
            "county": "NEW YORK"
        },
        "isBusinessYrs": "no",
        "isTaxId": "no",
        "name": "ABC",
        "businessType": "C",
        "established": "2020-09-30T18:30:00.000Z",
        "ein": "444444444"
    }
}